{"name":"base", "grid":[[{"0":"water"}, {"0":"water"}, {"0":"water"}, {"0":"water"}, {"0":"water"}, {"0":"water"}, {"0":"water"}, {"0":"water"}, {"0":"water"}, {"0":"water"}], [{"0":"water"}, {"0":"water", "1":"foam", "3":"sand", "6":"bridge_vertical"}, {"0":"water", "1":"foam", "3":"sand", "6":"bridge_vertical"}, {"0":"water", "1":"foam", "3":"sand", "5":"stairs"}, {"0":"water", "2":"terrace"}, {"0":"water"}, {"0":"water", "1":"foam", "5":"cliff"}, {"0":"water", "1":"foam", "2":"terrace", "4":"grass"}, {"0":"water", "2":"terrace", "3":"sand", "4":"grass"}, {"0":"water"}], [{"0":"water"}, {"0":"water", "1":"foam", "3":"sand", "6":"bridge_horizontal"}, {"0":"water", "1":"foam", "3":"sand"}, {"0":"water", "1":"foam", "3":"sand", "5":"stairs"}, {"0":"water", "2":"terrace", "6":"bridge_vertical"}, {"0":"water", "6":"bridge_vertical"}, {"0":"water", "1":"foam", "5":"cliff", "6":"bridge_vertical"}, {"0":"water", "2":"terrace", "3":"sand", "4":"grass", "6":"bridge_vertical"}, {"0":"water", "2":"terrace", "3":"sand"}, {"0":"water"}], [{"0":"water"}, {"0":"water", "6":"bridge_horizontal"}, {"0":"water"}, {"0":"water"}, {"0":"water"}, {"0":"water"}, {"0":"water", "1":"foam", "5":"stairs"}, {"0":"water", "2":"terrace", "4":"grass"}, {"0":"water", "2":"terrace", "3":"sand"}, {"0":"water"}], [{"0":"water"}, {"0":"water", "6":"bridge_horizontal"}, {"0":"water"}, {"0":"water"}, {"0":"water"}, {"0":"water"}, {"0":"water"}, {"0":"water", "1":"foam", "5":"cliff"}, {"0":"water", "2":"terrace", "3":"sand"}, {"0":"water"}], [{"0":"water"}, {"0":"water", "1":"foam", "6":"bridge_horizontal"}, {"0":"water", "1":"foam", "5":"stairs"}, {"0":"water", "1":"foam", "2":"terrace"}, {"0":"water", "1":"foam", "2":"terrace", "5":"cliff"}, {"0":"water", "2":"terrace"}, {"0":"water", "2":"terrace"}, {"0":"water", "1":"foam", "5":"cliff"}, {"0":"water", "2":"terrace", "3":"sand"}, {"0":"water"}], [{"0":"water"}, {"0":"water", "1":"foam", "6":"bridge_horizontal"}, {"0":"water", "1":"foam", "5":"stairs"}, {"0":"water", "1":"foam", "2":"terrace"}, {"0":"water", "1":"foam", "2":"terrace", "5":"cliff"}, {"0":"water", "2":"terrace"}, {"0":"water", "2":"terrace", "6":"bridge_vertical"}, {"0":"water", "1":"foam", "5":"cliff", "6":"bridge_vertical"}, {"0":"water", "2":"terrace", "3":"sand", "6":"bridge_vertical"}, {"0":"water"}], [{"0":"water"}, {"0":"water", "1":"foam", "6":"bridge_horizontal"}, {"0":"water", "1":"foam", "5":"stairs"}, {"0":"water", "1":"foam", "2":"terrace"}, {"0":"water", "1":"foam", "2":"terrace", "5":"cliff"}, {"0":"water", "2":"terrace"}, {"0":"water", "2":"terrace"}, {"0":"water"}, {"0":"water"}, {"0":"water"}], [{"0":"water"}, {"0":"water"}, {"0":"water"}, {"0":"water"}, {"0":"water"}, {"0":"water"}, {"0":"water"}, {"0":"water"}, {"0":"water"}, {"0":"water"}], [{}, {}, {}, {}, {}, {}, {}, {}, {}, {}]]}